{"weights": [0.8, 0.6, 0.3, 0.9], "result": 27}
{"weights": [0.4, 0.4, 0.8, 0.2], "result": 39}
{"weights": [0.1, 0.5, 0.6, 0.8], "result": 138}
{"weights": [0.5, 0.1, 0.5, 0.1], "result": 66}
{"weights": [0.9, 0.9, 0.6, 0.6], "result": 13}
{"weights": [0.4, 0.8, 0.8, 0.1], "result": 31}
{"weights": [0.9, 0.2, 0.8, 0.7], "result": 20}
{"weights": [0.7, 0.5, 0.6, 0.5], "result": 19}
{"weights": [0.4, 0.7, 0.9, 0.2], "result": 36}
{"weights": [0.2, 0.1, 0.3, 0.2], "result": 231}
{"weights": [0.3, 0.1, 0.6, 0.8], "result": 90}
{"weights": [0.1, 0.2, 0.3, 0.1], "result": 356}
{"weights": [0.2, 0.8, 0.9, 0.6], "result": 52}
{"weights": [0.6, 0.1, 0.2, 0.8], "result": 62}
{"weights": [0.7, 0.8, 0.7, 0.8], "result": 24}
{"weights": [0.1, 0.1, 0.5, 0.6], "result": 294}
{"weights": [0.2, 0.4, 0.9, 0.6], "result": 74}
{"weights": [0.8, 0.8, 0.2, 0.7], "result": 20}
{"weights": [0.8, 0.6, 0.9, 0.7], "result": 24}
{"weights": [0.3, 0.5, 0.5, 0.9], "result": 49}
{"weights": [0.7, 0.6, 0.4, 0.4], "result": 23}
{"weights": [0.1, 0.9, 0.4, 0.5], "result": 79}
{"weights": [0.4, 0.5, 0.7, 0.2], "result": 30}
{"weights": [0.2, 0.9, 0.9, 0.4], "result": 41}
{"weights": [0.7, 0.1, 0.9, 0.6], "result": 21}
{"weights": [0.5, 0.4, 0.6, 0.2], "result": 37}
{"weights": [0.1, 0.5, 0.3, 0.2], "result": 182}
{"weights": [0.7, 0.8, 0.1, 0.5], "result": 26}
{"weights": [0.6, 0.5, 0.7, 0.6], "result": 27}
{"weights": [0.1, 0.4, 0.7, 0.2], "result": 128}
{"weights": [0.6, 0.3, 0.8, 0.3], "result": 28}
{"weights": [0.9, 0.9, 0.4, 0.1], "result": 15}
{"weights": [0.2, 0.1, 0.1, 0.7], "result": 261}
{"weights": [0.4, 0.4, 0.5, 0.6], "result": 45}
{"weights": [0.5, 0.2, 0.7, 0.1], "result": 37}
{"weights": [0.4, 0.4, 0.4, 0.4], "result": 52}
{"weights": [0.8, 0.1, 0.2, 0.6], "result": 35}
{"weights": [0.9, 0.1, 0.6, 0.4], "result": 26}
{"weights": [0.4, 0.8, 0.2, 0.4], "result": 33}
{"weights": [0.2, 0.5, 0.3, 0.6], "result": 117}
{"weights": [0.5, 0.4, 0.4, 0.5], "result": 44}
{"weights": [0.7, 0.6, 0.2, 0.2], "result": 24}
{"weights": [0.8, 0.6, 0.7, 0.2], "result": 17}
{"weights": [0.9, 0.4, 0.4, 0.5], "result": 26}
{"weights": [0.6, 0.4, 0.3, 0.5], "result": 31}
{"weights": [0.5, 0.6, 0.1, 0.1], "result": 38}
{"weights": [0.5, 0.5, 0.8, 0.4], "result": 36}
{"weights": [0.5, 0.2, 0.8, 0.4], "result": 33}
{"weights": [0.2, 0.3, 0.3, 0.9], "result": 164}
{"weights": [0.8, 0.7, 0.2, 0.9], "result": 23}
{"weights": [0.6, 0.7, 0.9, 0.4], "result": 19}
{"weights": [0.5, 0.3, 0.4, 0.2], "result": 44}
{"weights": [0.3, 0.9, 0.1, 0.9], "result": 45}
{"weights": [0.9, 0.8, 0.6, 0.6], "result": 14}
{"weights": [0.7, 0.5, 0.6, 0.1], "result": 20}
{"weights": [0.2, 0.2, 0.3, 0.1], "result": 229}
{"weights": [0.6, 0.4, 0.5, 0.9], "result": 30}
{"weights": [0.6, 0.4, 0.5, 0.3], "result": 34}
{"weights": [0.2, 0.3, 0.3, 0.2], "result": 195}
{"weights": [0.6, 0.6, 0.3, 0.8], "result": 25}
{"weights": [0.1, 0.1, 0.2, 0.6], "result": 406}
{"weights": [0.6, 0.4, 0.5, 0.6], "result": 27}
{"weights": [0.5, 0.8, 0.4, 0.6], "result": 30}
{"weights": [0.3, 0.8, 0.4, 0.5], "result": 45}
{"weights": [0.5, 0.5, 0.1, 0.4], "result": 59}
{"weights": [0.9, 0.6, 0.3, 0.3], "result": 17}
{"weights": [0.3, 0.5, 0.2, 0.8], "result": 89}
{"weights": [0.6, 0.4, 0.8, 0.8], "result": 30}
{"weights": [0.5, 0.5, 0.2, 0.6], "result": 59}
{"weights": [0.1, 0.6, 0.1, 0.3], "result": 171}
{"weights": [0.5, 0.3, 0.1, 0.9], "result": 56}
{"weights": [0.3, 0.1, 0.1, 0.3], "result": 145}
{"weights": [0.8, 0.4, 0.9, 0.6], "result": 26}
{"weights": [0.9, 0.8, 0.9, 0.3], "result": 15}
{"weights": [0.6, 0.8, 0.9, 0.4], "result": 13}
{"weights": [0.6, 0.6, 0.4, 0.3], "result": 33}
{"weights": [0.6, 0.7, 0.4, 0.8], "result": 30}
{"weights": [0.6, 0.1, 0.4, 0.3], "result": 56}
{"weights": [0.4, 0.8, 0.6, 0.2], "result": 33}
{"weights": [0.7, 0.1, 0.3, 0.7], "result": 49}
{"weights": [0.6, 0.3, 0.4, 0.6], "result": 42}
{"weights": [0.6, 0.3, 0.4, 0.7], "result": 42}
{"weights": [0.9, 0.9, 0.3, 0.5], "result": 17}
{"weights": [0.6, 0.4, 0.8, 0.3], "result": 24}
{"weights": [0.9, 0.3, 0.5, 0.9], "result": 28}
{"weights": [0.1, 0.4, 0.6, 0.9], "result": 156}
{"weights": [0.1, 0.5, 0.7, 0.9], "result": 119}
{"weights": [0.4, 0.2, 0.7, 0.5], "result": 54}
{"weights": [0.6, 0.8, 0.6, 0.4], "result": 21}
{"weights": [0.5, 0.4, 0.5, 0.1], "result": 50}
{"weights": [0.4, 0.8, 0.3, 0.9], "result": 40}
{"weights": [0.6, 0.2, 0.2, 0.1], "result": 47}
